pyaupro/__init__.py
pyaupro/_implementation.py
pyaupro/_reference.py
pyaupro/_utilities.py
pyaupro-0.1.11.dist-info/METADATA
pyaupro-0.1.11.dist-info/WHEEL
pyaupro-0.1.11.dist-info/licenses/LICENSE
pyaupro-0.1.11.dist-info/RECORD
