Metadata-Version: 2.4
Name: pyaupro
Version: 0.1.11
Summary: Efficient per-region overlap (PRO) calculation implemented using torchmetrics.
Project-URL: Repository, https://github.com/davnn/pyaupro
Author-email: David Muhr <muhrdavid+github@gmail.com>
License: MIT License
License-File: LICENSE
Classifier: Development Status :: 3 - Alpha
Classifier: Intended Audience :: Developers
Classifier: Intended Audience :: Education
Classifier: Intended Audience :: Science/Research
Classifier: License :: OSI Approved :: MIT License
Classifier: Operating System :: MacOS
Classifier: Operating System :: Microsoft :: Windows
Classifier: Operating System :: POSIX
Classifier: Operating System :: Unix
Classifier: Programming Language :: Python :: 3 :: Only
Classifier: Programming Language :: Python :: 3.10
Classifier: Programming Language :: Python :: 3.11
Classifier: Programming Language :: Python :: 3.12
Classifier: Programming Language :: Python :: 3.13
Classifier: Topic :: Scientific/Engineering
Classifier: Topic :: Software Development :: Libraries
Classifier: Topic :: Utilities
Requires-Python: >=3.10
Requires-Dist: numpy>=1.17.0
Requires-Dist: scipy>=1.0.0
Requires-Dist: torchmetrics>=1.0.0
